monplugin/__init__.py
monplugin-0.6.3.dist-info/WHEEL
monplugin-0.6.3.dist-info/METADATA
monplugin-0.6.3.dist-info/RECORD
