Metadata-Version: 2.3
Name: monplugin
Version: 0.6.3
Summary: Partial python port of perls Monitoring::Plugin
Author-email: Danijel Tasov <danijel.tasov@consol.de>
Requires-Python: >= 3.6
Classifier: Development Status :: 3 - Alpha
Classifier: Topic :: System :: Monitoring
Classifier: License :: OSI Approved :: GNU General Public License v3 (GPLv3)
